{
  "teams": {
    "Paul": {
      "name": "Paul",
      "records": {
        "Jake": 1,
        "Brandon": 1
      },
      "wins": 2,
      "losses": 9,
      "division": "Dan Dan Noodles",
      "totalPoints": 1427.6,
      "projectedFuturePPG": 111.8
    },
    "Carter": {
      "name": "Carter",
      "records": {
        "Zach": 2,
        "Chris": 1,
        "Jeremy": 2,
        "Brandon": 1,
        "Jake": 1,
        "Mike": 1,
        "Holden": 1,
        "Paul": 1
      },
      "wins": 10,
      "losses": 1,
      "division": "3-Cup Chickens",
      "totalPoints": 2088.92,
      "projectedFuturePPG": 157.6
    },
    "Brandon": {
      "name": "Brandon",
      "records": {
        "Jeremy": 1,
        "Mike": 1,
        "Holden": 1,
        "Zach": 2,
        "Chris": 1,
        "Kevin": 1,
        "Jake": 1
      },
      "wins": 8,
      "losses": 3,
      "division": "3-Cup Chickens",
      "totalPoints": 1986.0300000000002,
      "projectedFuturePPG": 151.61
    },
    "Zach": {
      "name": "Zach",
      "records": {
        "Jeremy": 2,
        "Paul": 1,
        "Chris": 1
      },
      "wins": 4,
      "losses": 7,
      "division": "3-Cup Chickens",
      "totalPoints": 1661.35,
      "projectedFuturePPG": 130.95
    },
    "Holden": {
      "name": "Holden",
      "records": {
        "Chris": 1,
        "Paul": 2,
        "Mike": 1,
        "Jeremy": 1,
        "Zach": 1
      },
      "wins": 6,
      "losses": 5,
      "division": "Dan Dan Noodles",
      "totalPoints": 1915.1499999999999,
      "projectedFuturePPG": 149.35
    },
    "Chris": {
      "name": "Chris",
      "records": {
        "Paul": 1,
        "Mike": 2,
        "Kevin": 1,
        "Jake": 1
      },
      "wins": 5,
      "losses": 6,
      "division": "Dan Dan Noodles",
      "totalPoints": 1962.24,
      "projectedFuturePPG": 144.24
    },
    "Jeremy": {
      "name": "Jeremy",
      "records": {
        "Paul": 1,
        "Chris": 1,
        "Mike": 1
      },
      "wins": 3,
      "losses": 8,
      "division": "3-Cup Chickens",
      "totalPoints": 1743.36,
      "projectedFuturePPG": 131.84
    },
    "Mike": {
      "name": "Mike",
      "records": {
        "Paul": 1,
        "Holden": 1
      },
      "wins": 2,
      "losses": 9,
      "division": "Dan Dan Noodles",
      "totalPoints": 1480.31,
      "projectedFuturePPG": 123.99
    },
    "Jake": {
      "name": "Jake",
      "records": {
        "Kevin": 1,
        "Zach": 1,
        "Mike": 2,
        "Paul": 1,
        "Holden": 2
      },
      "wins": 7,
      "losses": 4,
      "division": "Dan Dan Noodles",
      "totalPoints": 1854.68,
      "projectedFuturePPG": 134.68
    },
    "Kevin": {
      "name": "Kevin",
      "records": {
        "Jeremy": 2,
        "Zach": 1,
        "Chris": 1,
        "Paul": 1,
        "Brandon": 1,
        "Mike": 1,
        "Carter": 1
      },
      "wins": 8,
      "losses": 3,
      "division": "3-Cup Chickens",
      "totalPoints": 1947.75,
      "projectedFuturePPG": 151.55
    }
  },
  "schedule": [
    {
      "home": "Kevin",
      "away": "Zach",
      "week": 12
    },
    {
      "home": "Holden",
      "away": "Chris",
      "week": 12
    },
    {
      "home": "Brandon",
      "away": "Jeremy",
      "week": 12
    },
    {
      "home": "Paul",
      "away": "Mike",
      "week": 12
    },
    {
      "home": "Carter",
      "away": "Jake",
      "week": 12
    },
    {
      "home": "Chris",
      "away": "Paul",
      "week": 13
    },
    {
      "home": "Carter",
      "away": "Brandon",
      "week": 13
    },
    {
      "home": "Mike",
      "away": "Zach",
      "week": 13
    },
    {
      "home": "Jake",
      "away": "Jeremy",
      "week": 13
    },
    {
      "home": "Holden",
      "away": "Kevin",
      "week": 13
    },
    {
      "home": "Kevin",
      "away": "Carter",
      "week": 14
    },
    {
      "home": "Zach",
      "away": "Holden",
      "week": 14
    },
    {
      "home": "Jake",
      "away": "Chris",
      "week": 14
    },
    {
      "home": "Paul",
      "away": "Jeremy",
      "week": 14
    },
    {
      "home": "Brandon",
      "away": "Mike",
      "week": 14
    }
  ]
}